{
  "pack_id": "oil_and_gas",
  "pack_name": "Oil and Gas",
  "pack_version": "v2025_01",
  "jurisdiction": "us",
  "effective_date": "2025-01-01",
  "last_reviewed": "2026-05-07",
  "status": "draft_starter_pack_requires_legal_review",
  "description": "Sector overlay for U.S. upstream, midstream, downstream, offshore, pipeline, drilling, production, environmental, safety, and petroleum operations documentation.",
  "metadata": {
    "scope": "United States sector overlay controls for Oil and Gas. Intended to be used with us/core_control_library.",
    "source_note": "Source basis is mapped from U.S. federal statutes, regulations, agency guidance, regulator materials, and sector frameworks available at rule-pack publication time. This starter pack is not legal advice and requires expert validation before production reliance. State, territorial, tribal, and local obligations may impose additional requirements.",
    "human_review_required": true,
    "external_knowledge_policy": "No external knowledge is introduced during document evaluation. Regulatory source mappings live only in this versioned rule pack.",
    "engine_compatibility": {
      "expected_registry_fields": [
        "rule_id",
        "rule_version",
        "title",
        "regulatory_domain",
        "summary",
        "evaluation",
        "metadata"
      ],
      "supported_strategies": [
        "any_signal_presence",
        "all_signal_presence",
        "absent_signals",
        "min_signal_count"
      ]
    },
    "primary_sources": [
      {
        "name": "BSEE offshore safety and environmental enforcement framework",
        "issuer": "Bureau of Safety and Environmental Enforcement",
        "url": "https://www.bsee.gov/",
        "used_for": [
          "offshore safety",
          "well control",
          "inspection",
          "environmental enforcement"
        ]
      },
      {
        "name": "BOEM offshore leasing and exploration framework",
        "issuer": "Bureau of Ocean Energy Management",
        "url": "https://www.boem.gov/oil-gas-energy",
        "used_for": [
          "offshore leasing",
          "exploration plans",
          "development plans"
        ]
      },
      {
        "name": "PHMSA pipeline safety regulations",
        "issuer": "Pipeline and Hazardous Materials Safety Administration",
        "url": "https://www.phmsa.dot.gov/regulations",
        "used_for": [
          "pipeline safety",
          "integrity management",
          "incident reporting"
        ]
      },
      {
        "name": "EPA oil and gas environmental compliance materials",
        "issuer": "U.S. Environmental Protection Agency",
        "url": "https://www.epa.gov/natural-gas-star-program",
        "used_for": [
          "air emissions",
          "methane",
          "environmental controls"
        ]
      },
      {
        "name": "FERC oil and natural gas regulation materials",
        "issuer": "Federal Energy Regulatory Commission",
        "url": "https://www.ferc.gov/industries-data/natural-gas",
        "used_for": [
          "interstate natural gas facilities",
          "tariffs",
          "certificates"
        ]
      }
    ]
  },
  "rules": [
    {
      "rule_id": "OILGAS-BSEE-001",
      "rule_version": "2025.01",
      "title": "Offshore safety, inspection, or BSEE compliance evidence is present",
      "regulatory_domain": "sector_regulator_requirements",
      "summary": "Checks for BSEE, offshore safety, well control, incident reporting, inspection, or environmental enforcement evidence.",
      "evaluation": {
        "strategy": "any_signal_presence",
        "search_mode": "substring",
        "case_sensitive": false,
        "excerpt_window": 180,
        "max_matches_per_signal": 5,
        "on_missing": "review_required",
        "on_partial": "review_required",
        "required_signals": [
          "BSEE",
          "offshore safety",
          "well control",
          "inspection",
          "incident reporting",
          "safety and environmental management",
          "SEMS"
        ]
      },
      "metadata": {
        "control_type": "sector_overlay",
        "applicability": "sector_specific_overlay",
        "evidence_expectation": "The reviewed document/document set should contain direct textual evidence for this control, or the engine should return missing/review_required according to the rule strategy.",
        "legal_review_required": true,
        "review_guidance": "A qualified U.S. legal/compliance reviewer must confirm applicability, legal sufficiency, federal/state interaction, and whether absence of textual evidence should be treated as non-compliance.",
        "source_basis": [
          "BSEE offshore safety and environmental enforcement framework"
        ],
        "legal_review_status": "draft_starter_pack_requires_legal_review"
      }
    },
    {
      "rule_id": "OILGAS-PHMSA-001",
      "rule_version": "2025.01",
      "title": "Pipeline safety, integrity management, or incident-reporting evidence is documented",
      "regulatory_domain": "sector_regulator_requirements",
      "summary": "Checks for PHMSA, pipeline safety, integrity management, operator qualification, emergency response, or incident reporting evidence.",
      "evaluation": {
        "strategy": "min_signal_count",
        "search_mode": "substring",
        "case_sensitive": false,
        "excerpt_window": 180,
        "max_matches_per_signal": 6,
        "required_signals": [
          "PHMSA",
          "pipeline safety",
          "integrity management",
          "operator qualification",
          "emergency response",
          "incident report",
          "49 CFR"
        ],
        "min_count": 2,
        "on_missing": "missing",
        "on_partial": "review_required",
        "on_prohibited_match": "failed"
      },
      "metadata": {
        "control_type": "sector_overlay",
        "applicability": "sector_specific_overlay",
        "evidence_expectation": "The reviewed document/document set should contain direct textual evidence for this control, or the engine should return missing/review_required according to the rule strategy.",
        "legal_review_required": true,
        "review_guidance": "A qualified U.S. legal/compliance reviewer must confirm applicability, legal sufficiency, federal/state interaction, and whether absence of textual evidence should be treated as non-compliance.",
        "source_basis": [
          "PHMSA pipeline safety regulations"
        ],
        "legal_review_status": "draft_starter_pack_requires_legal_review"
      }
    },
    {
      "rule_id": "OILGAS-BOEM-001",
      "rule_version": "2025.01",
      "title": "Offshore lease, exploration, or development authorization evidence is present",
      "regulatory_domain": "licensing",
      "summary": "Checks for BOEM lease, exploration plan, development plan, right-of-way, or offshore authorization evidence.",
      "evaluation": {
        "strategy": "any_signal_presence",
        "search_mode": "substring",
        "case_sensitive": false,
        "excerpt_window": 180,
        "max_matches_per_signal": 5,
        "on_missing": "review_required",
        "on_partial": "review_required",
        "required_signals": [
          "BOEM",
          "offshore lease",
          "exploration plan",
          "development plan",
          "right-of-way",
          "lease block",
          "approval"
        ]
      },
      "metadata": {
        "control_type": "sector_overlay",
        "applicability": "sector_specific_overlay",
        "evidence_expectation": "The reviewed document/document set should contain direct textual evidence for this control, or the engine should return missing/review_required according to the rule strategy.",
        "legal_review_required": true,
        "review_guidance": "A qualified U.S. legal/compliance reviewer must confirm applicability, legal sufficiency, federal/state interaction, and whether absence of textual evidence should be treated as non-compliance.",
        "source_basis": [
          "BOEM oil and gas energy materials"
        ],
        "legal_review_status": "draft_starter_pack_requires_legal_review"
      }
    },
    {
      "rule_id": "OILGAS-EPA-001",
      "rule_version": "2025.01",
      "title": "Air, methane, spill, or environmental controls are documented",
      "regulatory_domain": "sector_regulator_requirements",
      "summary": "Checks for methane, air emissions, SPCC, spill response, wastewater, produced water, or environmental monitoring evidence.",
      "evaluation": {
        "strategy": "min_signal_count",
        "search_mode": "substring",
        "case_sensitive": false,
        "excerpt_window": 180,
        "max_matches_per_signal": 6,
        "required_signals": [
          "methane",
          "air emissions",
          "SPCC",
          "spill response",
          "produced water",
          "wastewater",
          "environmental monitoring",
          "EPA"
        ],
        "min_count": 2,
        "on_missing": "missing",
        "on_partial": "review_required",
        "on_prohibited_match": "failed"
      },
      "metadata": {
        "control_type": "sector_overlay",
        "applicability": "sector_specific_overlay",
        "evidence_expectation": "The reviewed document/document set should contain direct textual evidence for this control, or the engine should return missing/review_required according to the rule strategy.",
        "legal_review_required": true,
        "review_guidance": "A qualified U.S. legal/compliance reviewer must confirm applicability, legal sufficiency, federal/state interaction, and whether absence of textual evidence should be treated as non-compliance.",
        "source_basis": [
          "EPA oil and gas environmental compliance materials"
        ],
        "legal_review_status": "draft_starter_pack_requires_legal_review"
      }
    }
  ]
}
